wip/__init__.py
wip/main.py
exegol_mcp-0.0.0a1.dist-info/WHEEL
exegol_mcp-0.0.0a1.dist-info/entry_points.txt
exegol_mcp-0.0.0a1.dist-info/METADATA
exegol_mcp-0.0.0a1.dist-info/RECORD
