Metadata-Version: 2.3
Name: exegol-mcp
Version: 0.0.0a1
Summary: MCP server for Exegol
Keywords: exegol,mcp,ctf
Author: Dramelac, Elliot Belt
Author-email: Dramelac <dramelac@pm.me>, Elliot Belt <felix.billieres1@gmail.com>
License: # Exegol Software License (ESL) - Version 1.0
Requires-Dist: exegol>=5.1.7
Requires-Dist: mcp>=1.23.3
Requires-Python: >=3.10
Project-URL: Documentation, https://docs.exegol.com
Project-URL: Homepage, https://exegol.com
Project-URL: Issues, https://github.com/ThePorgs/Exegol/issues
Project-URL: Repository, https://github.com/ThePorgs/Exegol
